inquirer_executor/__init__.py
inquirer_executor/inquirer_executor.py
inquirer_executor-0.1.3.dist-info/LICENSE
inquirer_executor-0.1.3.dist-info/METADATA
inquirer_executor-0.1.3.dist-info/WHEEL
inquirer_executor-0.1.3.dist-info/top_level.txt
inquirer_executor-0.1.3.dist-info/RECORD
