Metadata-Version: 2.1
Name: inquirer-executor
Version: 0.1.3
Summary: A package to tightly bind user choices to functionality. Based on python-inquirer.
Home-page: https://github.com/Neugierdsnase/python-inquirer-executor
Author: Konstantin Kovar
Author-email: mail@vomkonstant.in
License: MIT
Keywords: color terminal
Platform: UNKNOWN
Classifier: Programming Language :: Python :: 3.6
Classifier: Programming Language :: Python :: 3.7
Classifier: Environment :: Console
Classifier: Intended Audience :: Developers
Classifier: License :: OSI Approved :: MIT License
Classifier: Operating System :: OS Independent
Classifier: Topic :: Software Development :: User Interfaces
Classifier: Topic :: Software Development
Classifier: Topic :: Software Development :: Libraries :: Application Frameworks
Requires-Dist: inquirer (==2.6.3)
